MANIFEST.in
README.md
development.txt
requirements.txt
setup.py
suggestive/__init__.py
suggestive.egg-info/PKG-INFO
suggestive.egg-info/SOURCES.txt
suggestive.egg-info/dependency_links.txt
suggestive.egg-info/requires.txt
suggestive.egg-info/top_level.txt