Metadata-Version: 1.0
Name: suggestive
Version: 0.2.0
Summary: Magically add auto complete to your python project
Home-page: https://github.com/Yipit/suggestive
Author: Lincoln de Sousa, Fábio M. Costa
Author-email: lincoln@yipit.com, fabio@yipit.com
License: UNKNOWN
Platform: UNKNOWN
